inspect_py/__init__.py
inspect_py/cant_use_inp.py
inspect_py/fix_bug_inp.py
inspect_py/learn01.py
inspect_py/other.py
inspect_py/sandbox1_inp.py
inspect_py/utils.py
inspect_py/utils_inp.py
inspect_py-0.1.4.dist-info/METADATA
inspect_py-0.1.4.dist-info/WHEEL
inspect_py-0.1.4.dist-info/top_level.txt
inspect_py-0.1.4.dist-info/RECORD
