Metadata-Version: 2.1
Name: inspect-py
Version: 0.1.4
Summary: Expansion of inspect to help analyze and automate python code
Home-page: https://github.com/DearNorathee/inspect_py
Author: Dear Norathee
Author-email: noratee5@hotmail.com
License: MIT
Requires-Dist: pandas
Requires-Dist: py-string-tool >=0.1.4
Requires-Dist: python-wizard >=0.1.3
Requires-Dist: os-toolkit >=0.1.2
